id_manager/__init__.py
id_manager/apps.py
id_manager/services.py
id_manager-0.0.2.dist-info/METADATA
id_manager-0.0.2.dist-info/WHEEL
id_manager-0.0.2.dist-info/top_level.txt
id_manager-0.0.2.dist-info/RECORD
