Metadata-Version: 2.1
Name: id-manager
Version: 0.0.2
Summary: Task manager celery to django
Home-page: https://github.com/IgorDantasID/task-manager.git
Author: Igor Dantas de Aguiar
Author-email: igordantas91@icloud.com
License: MIT
Platform: UNKNOWN
Classifier: Programming Language :: Python :: 3
Classifier: License :: OSI Approved :: MIT License
Classifier: Operating System :: OS Independent
Requires-Python: >=3.7
Requires-Dist: Django (>=3)
